autodistill_albef/__init__.py
autodistill_albef/albef.py
autodistill_albef-0.1.0.dist-info/LICENSE
autodistill_albef-0.1.0.dist-info/METADATA
autodistill_albef-0.1.0.dist-info/WHEEL
autodistill_albef-0.1.0.dist-info/top_level.txt
autodistill_albef-0.1.0.dist-info/RECORD
