Metadata-Version: 2.1
Name: autodistill-albef
Version: 0.1.0
Summary: ALBEF module for use with Autodistill
Home-page: 
Author: Roboflow
Author-email: support@roboflow.com
Classifier: Programming Language :: Python :: 3
Classifier: License :: OSI Approved :: BSD License
Classifier: Operating System :: OS Independent
Requires-Python: >=3.7
License-File: LICENSE
Requires-Dist: transformers (==4.25)
Requires-Dist: torch
Requires-Dist: numpy
Requires-Dist: autodistill
Requires-Dist: supervision
Provides-Extra: dev
Requires-Dist: flake8 ; extra == 'dev'
Requires-Dist: black (==22.3.0) ; extra == 'dev'
Requires-Dist: isort ; extra == 'dev'
Requires-Dist: twine ; extra == 'dev'
Requires-Dist: pytest ; extra == 'dev'
Requires-Dist: wheel ; extra == 'dev'
